script_utils/__init__.py
script_utils/script_utils.py
script_utils-0.21.dist-info/METADATA
script_utils-0.21.dist-info/WHEEL
script_utils-0.21.dist-info/top_level.txt
script_utils-0.21.dist-info/RECORD
