Metadata-Version: 2.1
Name: script-utils
Version: 0.21
Summary: Script utils for PoDrodze :>
Home-page: UNKNOWN
Author: Mateusz Bieganski
Author-email: bieganski.m@wp.pl
License: UNKNOWN
Platform: UNKNOWN
Classifier: Programming Language :: Python :: 3
Classifier: License :: OSI Approved :: MIT License
Classifier: Operating System :: OS Independent
